hic2mcool/__init__.py
hic2mcool/hic2mcool.py
hic2mcool-0.0.1.dist-info/licenses/LICENSE
hic2mcool-0.0.1.dist-info/METADATA
hic2mcool-0.0.1.dist-info/WHEEL
hic2mcool-0.0.1.dist-info/entry_points.txt
hic2mcool-0.0.1.dist-info/top_level.txt
hic2mcool-0.0.1.dist-info/RECORD
