Metadata-Version: 2.4
Name: hic2mcool
Version: 0.0.1
Summary: A command-line utility for converting .hic to .mcool files
Author: Brydon Wall
License: MIT
Requires-Python: >=3.7
License-File: LICENSE
Requires-Dist: numpy
Requires-Dist: pandas
Requires-Dist: hic-straw
Requires-Dist: cooler
Requires-Dist: h5py
Dynamic: license-file
